[
    {"CN":"warCarimg1","imgurl":"../imgs/car2.jpg","biaoti":"420M/58 ELDORADO ","year":"1958"},
    {"CN":"warCarimg2","imgurl":"../imgs/car7.jpg","biaoti":"TIPO 60/61“鸟笼” ","year":"1959"},
    {"CN":"granimg1","imgurl":"../imgs/1500_Gran_Turismo_exterior.jpg","biaoti":"1500 Gran Turismo” ","year":"1947-1950"},
    {"CN":"granimg2","imgurl":"../imgs/2000_Gran_Turismo_exterior.jpg","biaoti":"2000 Gran Turismo” ","year":"1950-1951"},
    {"CN":"granimg3","imgurl":"../imgs/2000_Gran_Turismo_54_exterior.jpg","biaoti":"2000 Gran Turismo (54) ","year":" 1953-1957"},
    {"CN":"granimg4","imgurl":"../imgs/3500GT-3500GTI_exterior.jpg","biaoti":"3500GT - 3500GTI","year":"1957-1965"},
    {"CN":"granimg5","imgurl":"../imgs/3500_GT_GTI_Spyder_exterior.jpg","biaoti":"3500GT/3500GTI Spyder” ","year":" 1960-1965"},
    {"CN":"granimg6","imgurl":"../imgs/Sebring_first_series_exterior.jpg","biaoti":"Sebring - First series ","year":" 1962-1964"},
    {"CN":"granimg7","imgurl":"../imgs/Sebring_second_series-exterior_6.jpg","biaoti":"Sebring - Second Series ","year":"1964-1969"},
    {"CN":"granimg8","imgurl":"../imgs/Mistral_exterior_2.jpg","biaoti":"Mistral ","year":"1963-1969"},
    {"CN":"granimg9","imgurl":"../imgs/Mistral_Spyder_exterior_2.jpeg","biaoti":"Mistral Spyder ","year":"1964-1969"},
    {"CN":"granimg10","imgurl":"../imgs/5000_GT_exterior.jpg","biaoti":"5000GT ","year":"1959-1966"},
    {"CN":"granimg11","imgurl":"../imgs/Mexico_exterior.jpg","biaoti":"Mexico ","year":"1966-1972"},
    {"CN":"granimg12","imgurl":"../imgs//Ghibli_exterior.jpg","biaoti":"Ghibli ","year":"1967-1972"}, 
    {"CN":"granimg13","imgurl":"../imgs/Ghibli_exterior.jpg","biaoti":"Ghibli Spyder ","year":"1969-1973"}, 
    {"CN":"granimg14","imgurl":"../imgs/Indy_exterior.jpg","biaoti":"Indy ","year":"1969-1975"},
    {"CN":"granimg15","imgurl":"../imgs/Bora_exterior.jpg","biaoti":"Bora ","year":"1971-1978"},
    {"CN":"granimg16","imgurl":"../imgs/Khamsin_exterior.jpg","biaoti":"Khamsin ","year":" 1974-1982"},
    {"CN":"granimg17","imgurl":"../imgs/Kyalami_exterior.jpg","biaoti":"Kyalami","year":"1976-1983"},
    {"CN":"granimg18","imgurl":"../imgs/Merak-exterior.jpg","biaoti":"Merak ","year":" 1971-1982"},
    {"CN":"granimg19","imgurl":"../imgs/3200_GT_exterior.jpg","biaoti":"3200GT","year":" 1998-2002"},
    {"CN":"granimg20","imgurl":"../imgs/Spyder_exterior.jpg","biaoti":"Spyder","year":" 2001-2007"},
    {"CN":"granimg21","imgurl":"../imgs/Coupe_exterior.jpg","biaoti":"Coupé","year":" 2002-2007"},
    {"CN":"granimg22","imgurl":"../imgs/Gransport_exterior.jpg","biaoti":"GranSport, GranSport Spyder ","year":" 2004-2007"},
    {"CN":"quattroporteimg1","imgurl":"../imgs/Quattroporte_I_first_series_exterior.jpg","biaoti":"Quattroporte I - First series ","year":"1964-1966"},
    {"CN":"quattroporteimg2","imgurl":"../imgs/Quattroporte_I_second_series-exterior.jpg","biaoti":"Quattroporte I - Second series ","year":"1947-1950"},
    {"CN":"quattroporteimg3","imgurl":"../imgs/Quattroporte_II_exterior.jpg","biaoti":"Quattroporte II ","year":"1974-1978"},
    {"CN":"quattroporteimg4","imgurl":"../imgs/Quattroporte_III_exterior.jpg","biaoti":"Quattroporte III ","year":" 1979-1990"},
    {"CN":"quattroporteimg5","imgurl":"../imgs/Quattroporte-IV-Exterior.jpg","biaoti":"Quattroporte IV ","year":" 1994-1998 "},
    {"CN":"quattroporteimg6","imgurl":"../imgs/Quattroporte_IV-evoluzione-exterior.jpeg","biaoti":"Quattroporte IV Evoluzione ","year":" 1998-2001"},
    {"CN":"quattroporteimg7","imgurl":"../imgs/Quattroporte_V_Duoselect_exterior.jpg","biaoti":"Quattroporte V Duoselect ","year":"2003-2008"},
    {"CN":"quattroporteimg8","imgurl":"../imgs/Quattroporte_V_Automatica-exterior.jpg","biaoti":"Quattroporte V Automatica ","year":"2006-2008"},
    {"CN":"quattroporteimg9","imgurl":"../imgs/Quattroporte_V_Restyling-exterior.jpg","biaoti":"Quattroporte V Restyling ","year":"  2008-2013   "},
    {"CN":"biturboimg1","imgurl":"../imgs/Biturbo_exterior.jpg","biaoti":"Biturbo ","year":"1981-1988"},
    {"CN":"biturboimg2","imgurl":"../imgs/Biturbo_Export-exterior.jpeg","biaoti":"Biturbo Export ","year":"1983-1991"},
    {"CN":"biturboimg3","imgurl":"../imgs/222_exterior.jpg","biaoti":"222 - 2.24v","year":"1988-1993"},
    {"CN":"biturboimg4","imgurl":"../imgs/222_Export_exterior.jpg","biaoti":"222 Export","year":" 1988-1994"},
    {"CN":"biturboimg5","imgurl":"../imgs/425-exterior.jpeg","biaoti":"425 ","year":"1983-1989"},
    {"CN":"biturboimg6","imgurl":"../imgs/420_exterior.jpg","biaoti":"420 ","year":"1985-1988"},
    {"CN":"biturboimg7","imgurl":"../imgs//430_exterior.jpg","biaoti":"430","year":" 1987-1994"},
    {"CN":"biturboimg8","imgurl":"../imgs/422_exterior.jpg","biaoti":"422 - 4.18v - 4.24v ","year":"1988-1993"},
    {"CN":"biturboimg9","imgurl":"../imgs/Biturbo_Spyder_exterior.jpg","biaoti":"Biturbo Spyder","year":" 1984-1991"},
    {"CN":"specialimg1","imgurl":"../imgs/A6GCS_Berlinetta_exterior.jpg","biaoti":"A6GCS BERLINETTA PININ FARINA ","year":"1953-1954"},
    {"CN":"specialimg2","imgurl":"../imgs/Barchetta_exterior.jpg","biaoti":"BARCHETTA","year":"1992-1993"},
    {"CN":"specialimg3","imgurl":"../imgs/MC12_exterior.jpg","biaoti":"MC12 ","year":"2004-2005"},
    {"CN":"specialimg4","imgurl":"../imgs/MC12_versione_corse_exterior.jpg","biaoti":"MC12 VERSIONE CORSE ","year":" 2006-2007"}
]